POKE_DONPOLLO/__init__.py
POKE_DONPOLLO/pokemon.csv
POKE_DONPOLLO/ramdom_pokemon.py
poke_frm_donpolloloco-1.0.2.dist-info/METADATA
poke_frm_donpolloloco-1.0.2.dist-info/WHEEL
poke_frm_donpolloloco-1.0.2.dist-info/top_level.txt
poke_frm_donpolloloco-1.0.2.dist-info/RECORD
